gisaxs_xpcs/__init__.py
gisaxs_xpcs/common_functions.py
gisaxs_xpcs/common_tools.py
gisaxs_xpcs/extract_data.py
gisaxs_xpcs/gisaxs_parameters.py
gisaxs_xpcs/manage_h5_data.py
gisaxs_xpcs/metadata_obj.py
gisaxs_xpcs/plot_report.py
gisaxs_xpcs/read_edf.py
gisaxs_xpcs/xpcs.py
GISAXS_XPCS-0.1.7.dist-info/METADATA
GISAXS_XPCS-0.1.7.dist-info/WHEEL
GISAXS_XPCS-0.1.7.dist-info/top_level.txt
GISAXS_XPCS-0.1.7.dist-info/RECORD
