Metadata-Version: 2.1
Name: GISAXS-XPCS
Version: 0.1.7
Summary: Package for GISAXS-XPCS analysis. For internal use within Shreiber lab.
Home-page: UNKNOWN
Author: Vladimir Starostin
Author-email: vladimir.starostin@uni-tuebingen.de
License: MIT
Platform: UNKNOWN
Requires-Dist: numpy
Requires-Dist: pandas
Requires-Dist: matplotlib
Requires-Dist: scipy
Requires-Dist: h5py
Requires-Dist: tqdm
Requires-Dist: jupyter
